pyrustic/__init__.py
pyrustic/__main__.py
pyrustic/app.py
pyrustic/hello.py
pyrustic/hooking/__init__.py
pyrustic/hooking/ante_build_hook.py
pyrustic/hooking/ante_release_hook.py
pyrustic/hooking/post_build_hook.py
pyrustic/hooking/post_release_hook.py
pyrustic/hooking/private
pyrustic/manager/__init__.py
pyrustic/manager/cmdline.py
pyrustic/manager/constant.py
pyrustic/manager/oneline.py
pyrustic/manager/private
pyrustic/manager/core/__init__.py
pyrustic/manager/core/building.py
pyrustic/manager/core/funcs.py
pyrustic/manager/core/github_client.py
pyrustic/manager/core/initialization.py
pyrustic/manager/core/installation.py
pyrustic/manager/core/lite_test_runner.py
pyrustic/manager/core/private
pyrustic/manager/core/publishing.py
pyrustic/manager/core/pymisc.py
pyrustic/manager/default_json/PyrusticData/manager_shared_data_default.json
pyrustic/manager/default_json/pyrustic_data/build_report_default.json
pyrustic/manager/default_json/pyrustic_data/hooking_default.json
pyrustic/manager/default_json/pyrustic_data/hubstore_default.json
pyrustic/manager/default_json/pyrustic_data/release_info_default.json
pyrustic/manager/handler/__init__.py
pyrustic/manager/handler/add_handler.py
pyrustic/manager/handler/build_handler.py
pyrustic/manager/handler/hub_handler.py
pyrustic/manager/handler/init_handler.py
pyrustic/manager/handler/link_handler.py
pyrustic/manager/handler/private
pyrustic/manager/handler/publish_handler.py
pyrustic/manager/handler/recent_handler.py
pyrustic/manager/handler/relink_handler.py
pyrustic/manager/handler/run_handler.py
pyrustic/manager/handler/target_handler.py
pyrustic/manager/handler/unlink_handler.py
pyrustic/manager/handler/version_handler.py
pyrustic/manager/template/ante_build_hook_template.txt
pyrustic/manager/template/ante_release_hook_template.txt
pyrustic/manager/template/changelog_template.txt
pyrustic/manager/template/gitignore_template.txt
pyrustic/manager/template/latest_release_template.txt
pyrustic-0.1.15.dist-info/LICENSE
pyrustic-0.1.15.dist-info/METADATA
pyrustic-0.1.15.dist-info/WHEEL
pyrustic-0.1.15.dist-info/entry_points.txt
pyrustic-0.1.15.dist-info/top_level.txt
pyrustic-0.1.15.dist-info/RECORD
