Metadata-Version: 2.1
Name: pyrustic
Version: 0.1.15
Summary: Collection of lightweight Python projects that share the same policy
Home-page: https://github.com/pyrustic/pyrustic
Author: Pyrustic Evangelist
Author-email: rusticalex@yahoo.com
Maintainer: Pyrustic Evangelist
Maintainer-email: rusticalex@yahoo.com
License: MIT
Keywords: pyrustic
Platform: UNKNOWN
Classifier: Programming Language :: Python :: 3
Classifier: License :: OSI Approved :: MIT License
Classifier: Operating System :: OS Independent
Requires-Python: >=3.5
License-File: LICENSE
